adafruit_circuitpython_displayio_flipclock-1.1.8.dist-info/licenses/LICENSE
adafruit_displayio_flipclock/__init__.py
adafruit_displayio_flipclock/flip_clock.py
adafruit_displayio_flipclock/flip_digit.py
adafruit_circuitpython_displayio_flipclock-1.1.8.dist-info/METADATA
adafruit_circuitpython_displayio_flipclock-1.1.8.dist-info/WHEEL
adafruit_circuitpython_displayio_flipclock-1.1.8.dist-info/top_level.txt
adafruit_circuitpython_displayio_flipclock-1.1.8.dist-info/RECORD
