Metadata-Version: 2.4
Name: adafruit-circuitpython-displayio-flipclock
Version: 1.1.8
Summary: DisplayIO widgets for showing flip clock style animattions changing from one number to another.
Author-email: Adafruit Industries <circuitpython@adafruit.com>
License: MIT
Project-URL: Homepage, https://github.com/adafruit/Adafruit_CircuitPython_DisplayIO_FlipClock
Keywords: adafruit,blinka,circuitpython,micropython,displayio_flipclock,displayio,clock,time,flipclock,display,lcd,widget,ui,number
Classifier: Intended Audience :: Developers
Classifier: Topic :: Software Development :: Libraries
Classifier: Topic :: Software Development :: Embedded Systems
Classifier: Topic :: System :: Hardware
Classifier: License :: OSI Approved :: MIT License
Classifier: Programming Language :: Python :: 3
License-File: LICENSE
Requires-Dist: Adafruit-Blinka
Requires-Dist: adafruit-circuitpython-busdevice
Requires-Dist: adafruit-circuitpython-register
Requires-Dist: adafruit-circuitpython-displayio-layout
Provides-Extra: optional
Dynamic: license-file
